pcdt_scraper/__init__.py
pcdt_scraper/main.py
pcdt_scraper-1.0.1.dist-info/METADATA
pcdt_scraper-1.0.1.dist-info/WHEEL
pcdt_scraper-1.0.1.dist-info/top_level.txt
pcdt_scraper-1.0.1.dist-info/RECORD
