Metadata-Version: 2.2
Name: pcdt-scraper
Version: 1.0.1
Summary: A PyChromeDevTools based WebScraper and selenium like syntax.
Home-page: https://github.com/jakbin/pcdt-scraper
Author: Jak Bin
Project-URL: Bug Tracker, https://github.com/jakbin/pcdt-scraper/issues
Keywords: webscraper,scraper,web-scraper,pcdt-scraper
Classifier: Programming Language :: Python :: 3
Classifier: License :: OSI Approved :: MIT License
Classifier: Operating System :: OS Independent
Requires-Python: >=3.6
Requires-Dist: bs4
Requires-Dist: PyChromeDevTools
Dynamic: author
Dynamic: classifier
Dynamic: description
Dynamic: description-content-type
Dynamic: home-page
Dynamic: keywords
Dynamic: project-url
Dynamic: requires-dist
Dynamic: requires-python
Dynamic: summary
